muffin/__init__.py
muffin/app.py
muffin/constants.py
muffin/errors.py
muffin/handler.py
muffin/manage.py
muffin/plugins.py
muffin/py.typed
muffin/pytest.py
muffin/types.py
muffin/utils.py
muffin-1.2.0.dist-info/METADATA
muffin-1.2.0.dist-info/WHEEL
muffin-1.2.0.dist-info/entry_points.txt
muffin-1.2.0.dist-info/RECORD
