Metadata-Version: 2.4
Name: muffin
Version: 1.2.0
Summary: Muffin is a fast, simple and asyncronous web-framework for Python 3 (asyncio, trio, curio)
Project-URL: Homepage, https://github.com/klen/muffin
Project-URL: Repository, https://github.com/klen/muffin
Project-URL: Documentation, https://klen.github.io/muffin
Project-URL: changelog, https://raw.githubusercontent.com/klen/muffin/master/CHANGELOG.md
Author-email: Kirill Klenov <horneds@gmail.com>
License-Expression: MIT
Keywords: asgi,asyncio,curio,trio,web,web framework
Classifier: Development Status :: 5 - Production/Stable
Classifier: Framework :: AsyncIO
Classifier: Framework :: Trio
Classifier: Intended Audience :: Developers
Classifier: License :: OSI Approved :: MIT License
Classifier: Programming Language :: Python
Classifier: Programming Language :: Python :: 3
Classifier: Programming Language :: Python :: 3.10
Classifier: Programming Language :: Python :: 3.11
Classifier: Programming Language :: Python :: 3.12
Classifier: Programming Language :: Python :: 3.13
Classifier: Programming Language :: Python :: Implementation :: PyPy
Classifier: Topic :: Internet :: WWW/HTTP
Requires-Python: >=3.10
Requires-Dist: asgi-tools<2,>=1.3.3
Requires-Dist: modconfig<2,>=1
Requires-Dist: ujson
Provides-Extra: standard
Requires-Dist: gunicorn<21,>=20.1.0; extra == 'standard'
Requires-Dist: uvicorn[standard]<0.22,>=0.21.1; extra == 'standard'
